pythonapm/__init__.py
pythonapm/agent.py
pythonapm/agentfactory.py
pythonapm/constants.py
pythonapm/context.py
pythonapm/logger.py
pythonapm/test_agent.py
pythonapm/test_agentfactory.py
pythonapm/test_context.py
pythonapm/test_logger.py
pythonapm/test_util.py
pythonapm/util.py
pythonapm/collector/__init__.py
pythonapm/collector/connhandler.py
pythonapm/collector/datahandler.py
pythonapm/collector/insinfo.py
pythonapm/collector/reqhandler.py
pythonapm/collector/reshandler.py
pythonapm/collector/test_connhandler.py
pythonapm/collector/test_datahandler.py
pythonapm/collector/test_insinfo.py
pythonapm/collector/test_reqhandler.py
pythonapm/collector/test_reshandler.py
pythonapm/config/__init__.py
pythonapm/config/configuration.py
pythonapm/config/test_configuration.py
pythonapm/contrib/__init__.py
pythonapm/contrib/django/__init__.py
pythonapm/contrib/django/apps.py
pythonapm/contrib/django/test_wrapper.py
pythonapm/contrib/django/wrapper.py
pythonapm/instrumentation/__init__.py
pythonapm/instrumentation/modules.py
pythonapm/instrumentation/test_instrument.py
pythonapm/instrumentation/test_wrapper.py
pythonapm/instrumentation/wrapper.py
pythonapm/instrumentation/packages/__init__.py
pythonapm/instrumentation/packages/django.py
pythonapm/instrumentation/packages/flask.py
pythonapm/instrumentation/packages/jinja2.py
pythonapm/metric/__init__.py
pythonapm/metric/metricstore.py
pythonapm/metric/test_metricstore.py
pythonapm/metric/test_txn.py
pythonapm/metric/test_txnmetric.py
pythonapm/metric/txn.py
pythonapm/metric/txnmetric.py
pythonapm-1.0.3.dist-info/METADATA
pythonapm-1.0.3.dist-info/WHEEL
pythonapm-1.0.3.dist-info/top_level.txt
pythonapm-1.0.3.dist-info/RECORD
