Metadata-Version: 2.1
Name: pythonapm
Version: 1.0.3
Summary: Monitor Django and Flask python web applications
Home-page: https://nextapm.dev
Author: Chan Anan
Author-email: chan@nextapm.dev
License: MIT
Platform: UNKNOWN
Requires-Python: >=3.6
Requires-Dist: requests
